[
	{
		"abbr": "AF",
		"handle": null,
		"havePhoto": true,
		"name": null,
		"width": 640,
		"height": 480
	},
	{
		"abbr": "AL",
		"handle": "adventurealbania",
		"havePhoto": true,
		"height": 563,
		"name": "Adventure Albania",
		"width": 750
	},
	{
		"abbr": "DZ",
		"handle": null,
		"havePhoto": false,
		"name": null
	},
	{
		"abbr": "AD",
		"handle": null,
		"havePhoto": false,
		"name": null
	},
	{
		"abbr": "AO",
		"handle": null,
		"havePhoto": false,
		"name": null
	},
	{
		"abbr": "AG",
		"handle": null,
		"havePhoto": false,
		"name": null
	},
	{
		"abbr": "AR",
		"handle": null,
		"havePhoto": false,
		"name": null
	},
	{
		"abbr": "AM",
		"handle": null,
		"havePhoto": false,
		"name": null
	},
	{
		"abbr": "AU",
		"handle": null,
		"havePhoto": false,
		"name": null
	},
	{
		"abbr": "AT",
		"handle": null,
		"havePhoto": false,
		"name": null
	},
	{
		"abbr": "AZ",
		"handle": null,
		"havePhoto": false,
		"name": null
	},
	{
		"abbr": "BS",
		"handle": null,
		"havePhoto": false,
		"name": null
	},
	{
		"abbr": "BH",
		"handle": null,
		"havePhoto": false,
		"name": null
	},
	{
		"abbr": "BD",
		"handle": null,
		"havePhoto": false,
		"name": null
	},
	{
		"abbr": "BB",
		"handle": null,
		"havePhoto": false,
		"name": null
	},
	{
		"havePhoto": true,
		"name": "Andrey Kukharenko",
		"handle": "",
		"width": 640,
		"height": 427,
		"abbr": "BY"
	},
	{
		"abbr": "BE",
		"handle": "jorgefdezsalas",
		"havePhoto": true,
		"height": 480,
		"name": "Jorge Fernández Salas",
		"width": 640
	},
	{
		"havePhoto": true,
		"name": "Meritt Thomas",
		"handle": "merittthomas",
		"width": 640,
		"height": 427,
		"abbr": "BZ"
	},
	{
		"havePhoto": true,
		"name": "Iwaria Inc.",
		"handle": "iwaria",
		"width": 640,
		"height": 426,
		"abbr": "BJ"
	},
	{
		"havePhoto": true,
		"name": "Raul Taciu",
		"handle": "raultaciu",
		"width": 640,
		"height": 427,
		"abbr": "BT"
	},
	{
		"havePhoto": true,
		"name": "Andrea Huls Pareja",
		"handle": "andreahuls",
		"width": 640,
		"height": 427,
		"abbr": "BO"
	},
	{
		"abbr": "BA",
		"havePhoto": true,
		"name": "Luka Korica",
		"handle": "lkorica_photo",
		"width": 640,
		"height": 479
	},
	{
		"havePhoto": true,
		"name": "Wynand Uys",
		"handle": "wynand_uys",
		"width": 640,
		"height": 398,
		"abbr": "BW"
	},
	{
		"abbr": "BR",
		"handle": "smiley_shotz",
		"havePhoto": true,
		"height": 960,
		"name": "Marianna Smiley",
		"width": 640
	},
	{
		"havePhoto": true,
		"name": "Hung Li",
		"handle": "hungli_photo",
		"width": 640,
		"height": 360,
		"abbr": "BN"
	},
	{
		"abbr": "BG",
		"handle": "dannyspasov",
		"havePhoto": true,
		"height": 800,
		"name": "Dannyel Spasov",
		"width": 640
	},
	{
		"havePhoto": true,
		"name": "YODA Adaman",
		"handle": "adam_yod",
		"width": 640,
		"height": 480,
		"abbr": "BF"
	},
	{
		"havePhoto": true,
		"name": "Mika R",
		"handle": "jsmika",
		"width": 640,
		"height": 480,
		"abbr": "BI"
	},
	{
		"havePhoto": true,
		"name": "Dick Hoskins",
		"handle": "healthmaps",
		"width": 640,
		"height": 480,
		"abbr": "KH"
	},
	{
		"havePhoto": true,
		"name": "Edouard TAMBA",
		"handle": "tamba",
		"width": 640,
		"height": 394,
		"abbr": "CM"
	},
	{
		"abbr": "CA",
		"handle": "thirdworldhippy",
		"havePhoto": true,
		"height": 937,
		"name": "Mwangi Gatheca",
		"width": 750
	},
	{
		"havePhoto": true,
		"name": "Florian K.",
		"handle": "flouchy",
		"width": 640,
		"height": 426,
		"abbr": "CV"
	},
	{
		"havePhoto": true,
		"name": "Jack Lajoie",
		"handle": "jack_lajoie",
		"width": 640,
		"height": 360,
		"abbr": "KY"
	},
	{
		"abbr": "CF",
		"havePhoto": true,
		"name": "redcharlie",
		"handle": "redcharlie",
		"width": 640,
		"height": 427
	},
	{
		"abbr": "TD",
		"handle": null,
		"havePhoto": false,
		"name": null
	},
	{
		"havePhoto": true,
		"name": "Olga Stalska",
		"handle": "stalskaya",
		"width": 640,
		"height": 427,
		"abbr": "CL"
	},
	{
		"havePhoto": true,
		"name": "Aaron Greenwood",
		"handle": "onevibe",
		"width": 640,
		"height": 427,
		"abbr": "CN"
	},
	{
		"abbr": "CO",
		"havePhoto": true,
		"name": "Janet Restrepo",
		"handle": "janettypa_ph",
		"width": 640,
		"height": 418
	},
	{
		"abbr": "KM",
		"handle": null,
		"havePhoto": false,
		"name": null
	},
	{
		"abbr": "CG",
		"havePhoto": true,
		"name": "Trésor Kande",
		"handle": "travyskande",
		"width": 640,
		"height": 427
	},
	{
		"havePhoto": true,
		"name": "Gina Lemafa",
		"handle": "geens",
		"width": 640,
		"height": 480,
		"abbr": "CK"
	},
	{
		"abbr": "CR",
		"handle": "fabian_marin1",
		"havePhoto": true,
		"height": 1125,
		"name": "Fabian Marin Zuñiga",
		"width": 750
	},
	{
		"abbr": "CI",
		"havePhoto": true,
		"name": "Eva Blue",
		"handle": "evablue",
		"width": 640,
		"height": 423
	},
	{
		"havePhoto": true,
		"name": "Spencer Davis",
		"handle": "spencerdavis",
		"width": 640,
		"height": 426,
		"abbr": "HR"
	},
	{
		"havePhoto": true,
		"name": "Jennifer Chen",
		"handle": "jnnfrchn",
		"width": 640,
		"height": 427,
		"abbr": "CU"
	},
	{
		"havePhoto": true,
		"name": "Athina Vrikki",
		"handle": "athina_vr",
		"width": 640,
		"height": 545,
		"abbr": "CY"
	},
	{
		"havePhoto": true,
		"name": "Mike Swigunski",
		"handle": "mike_swigunski",
		"width": 640,
		"height": 480,
		"abbr": "CZ"
	},
	{
		"abbr": "CD",
		"havePhoto": true,
		"name": "Johnnathan Tshibangu",
		"handle": "misterjo",
		"width": 640,
		"height": 427
	},
	{
		"abbr": "DK",
		"handle": "potapenko",
		"havePhoto": true,
		"height": 640,
		"name": "Maksym Potapenko",
		"width": 640
	},
	{
		"havePhoto": true,
		"name": "Lesly Derksen",
		"handle": "lderksen",
		"width": 640,
		"height": 480,
		"abbr": "DJ"
	},
	{
		"havePhoto": true,
		"name": "iSAW Company",
		"handle": "isaw",
		"width": 640,
		"height": 360,
		"abbr": "DM"
	},
	{
		"havePhoto": true,
		"name": "Juan Fernández",
		"handle": "juanluisf",
		"width": 640,
		"height": 425,
		"abbr": "DO"
	},
	{
		"havePhoto": true,
		"name": "Reiseuhu",
		"handle": "reiseuhu",
		"width": 640,
		"height": 480,
		"abbr": "EC"
	},
	{
		"havePhoto": true,
		"name": "Flying Carpet",
		"handle": "flying_carpet_tours",
		"width": 640,
		"height": 427,
		"abbr": "EG"
	},
	{
		"havePhoto": true,
		"name": "Enrique Alarcon",
		"handle": "qikealarcon",
		"width": 640,
		"height": 335,
		"abbr": "SV"
	},
	{
		"havePhoto": true,
		"name": "Cristian Tejeda",
		"handle": "cristejeda_ph",
		"width": 640,
		"height": 425,
		"abbr": "GQ"
	},
	{
		"abbr": "ER",
		"handle": null,
		"havePhoto": false,
		"name": null
	},
	{
		"abbr": "EE",
		"handle": "juliusjansson",
		"havePhoto": true,
		"height": 1125,
		"name": "Julius Jansson",
		"width": 750
	},
	{
		"havePhoto": true,
		"name": "S&apos;mile Vilakati",
		"handle": "smile_art",
		"width": 640,
		"height": 427,
		"abbr": "SZ"
	},
	{
		"havePhoto": true,
		"name": "Erik Hathaway",
		"handle": "erikhathaway",
		"width": 640,
		"height": 413,
		"abbr": "ET"
	},
	{
		"havePhoto": true,
		"name": "Yuriy Rzhemovskiy",
		"handle": "yuriyr",
		"width": 640,
		"height": 427,
		"abbr": "FK"
	},
	{
		"havePhoto": true,
		"name": "Max",
		"handle": "imcolourblind",
		"width": 640,
		"height": 425,
		"abbr": "FJ"
	},
	{
		"abbr": "FI",
		"handle": "hendrikmorkel",
		"havePhoto": true,
		"height": 427,
		"name": "Hendrik Morkel",
		"width": 640
	},
	{
		"abbr": "FR",
		"handle": "kalimullin",
		"havePhoto": true,
		"height": 960,
		"name": "Ilnur Kalimullin",
		"width": 640
	},
	{
		"havePhoto": true,
		"name": "Flow Flo",
		"handle": "floow",
		"width": 640,
		"height": 427,
		"abbr": "GF"
	},
	{
		"havePhoto": true,
		"name": "JEaLiFe Pictures",
		"handle": "jealife_pictures",
		"width": 640,
		"height": 427,
		"abbr": "GA"
	},
	{
		"havePhoto": true,
		"name": "Kurt Cotoaga",
		"handle": "kydroon",
		"width": 640,
		"height": 360,
		"abbr": "GM"
	},
	{
		"havePhoto": true,
		"name": "Polina Lukianets",
		"handle": "pauline_lu",
		"width": 640,
		"height": 480,
		"abbr": "GE"
	},
	{
		"abbr": "DE",
		"handle": "electerious",
		"havePhoto": true,
		"height": 960,
		"name": "Tobias Reich",
		"width": 640
	},
	{
		"havePhoto": true,
		"name": "Yoel Winkler",
		"handle": "yoel100",
		"width": 640,
		"height": 511,
		"abbr": "GH"
	},
	{
		"abbr": "GR",
		"handle": "despinagalani",
		"havePhoto": true,
		"height": 853,
		"name": "Despina Galani",
		"width": 640
	},
	{
		"havePhoto": true,
		"name": "Annie Spratt",
		"handle": "anniespratt",
		"width": 640,
		"height": 427,
		"abbr": "GL"
	},
	{
		"havePhoto": true,
		"name": "Hugh Whyte",
		"handle": "opixels",
		"width": 640,
		"height": 360,
		"abbr": "GD"
	},
	{
		"havePhoto": true,
		"name": "Rodrigo Escalante",
		"handle": "rodmantgt",
		"width": 640,
		"height": 427,
		"abbr": "GT"
	},
	{
		"abbr": "GN",
		"handle": null,
		"havePhoto": false,
		"name": null
	},
	{
		"havePhoto": true,
		"name": "Tim Oun",
		"handle": "timoun",
		"width": 640,
		"height": 439,
		"abbr": "GW"
	},
	{
		"havePhoto": true,
		"name": "Dinesh Chandrapal",
		"handle": "oudai1926",
		"width": 640,
		"height": 428,
		"abbr": "GY"
	},
	{
		"havePhoto": true,
		"name": "Alex Polinis",
		"handle": "apolinis",
		"width": 640,
		"height": 360,
		"abbr": "HT"
	},
	{
		"havePhoto": true,
		"name": "Héctor Emilio Gonzalez",
		"handle": "hectoremilio",
		"width": 640,
		"height": 360,
		"abbr": "HN"
	},
	{
		"havePhoto": true,
		"name": "Ervin Lukacs",
		"handle": "lukerv4",
		"width": 640,
		"height": 427,
		"abbr": "HU"
	},
	{
		"abbr": "IS",
		"handle": "tompodmore86",
		"havePhoto": true,
		"height": 427,
		"name": "Tom Podmore",
		"width": 640
	},
	{
		"havePhoto": true,
		"name": "Julian Yu",
		"handle": "littlej1428",
		"width": 640,
		"height": 427,
		"abbr": "IN"
	},
	{
		"havePhoto": true,
		"name": "Jeremy Bishop",
		"handle": "jeremybishop",
		"width": 640,
		"height": 427,
		"abbr": "ID"
	},
	{
		"havePhoto": true,
		"name": "Faruk Kaymak",
		"handle": "fkaymak",
		"width": 640,
		"height": 427,
		"abbr": "IR"
	},
	{
		"havePhoto": true,
		"name": "Saad Salim",
		"handle": "saadx",
		"width": 640,
		"height": 427,
		"abbr": "IQ"
	},
	{
		"abbr": "IE",
		"handle": "wiseguyinthesky",
		"havePhoto": true,
		"height": 938,
		"name": "Paul Costello",
		"width": 750
	},
	{
		"havePhoto": true,
		"name": "Shai Pal",
		"handle": "shaipal",
		"width": 640,
		"height": 480,
		"abbr": "IL"
	},
	{
		"havePhoto": true,
		"name": "Dan Novac",
		"handle": "dnovac",
		"width": 640,
		"height": 428,
		"abbr": "IT"
	},
	{
		"havePhoto": true,
		"name": "Lakeisha Bennett",
		"handle": "lakeishajannell",
		"width": 640,
		"height": 427,
		"abbr": "JM"
	},
	{
		"havePhoto": true,
		"name": "ZHENYU LUO",
		"handle": "mrnuclear",
		"width": 640,
		"height": 427,
		"abbr": "JP"
	},
	{
		"havePhoto": true,
		"name": "Emile Guillemot",
		"handle": "emilegt",
		"width": 640,
		"height": 426,
		"abbr": "JO"
	},
	{
		"havePhoto": true,
		"name": "Uladzislau Petrushkevich",
		"handle": "vladuken",
		"width": 640,
		"height": 427,
		"abbr": "KZ"
	},
	{
		"havePhoto": true,
		"name": "Sergey Pesterev",
		"handle": "sickle",
		"width": 640,
		"height": 963,
		"abbr": "KE"
	},
	{
		"havePhoto": true,
		"name": "Winston Chen",
		"handle": "winstonchen",
		"width": 640,
		"height": 427,
		"abbr": "KI"
	},
	{
		"havePhoto": true,
		"name": "Ahmad Mohammed",
		"handle": "amed10",
		"width": 640,
		"height": 384,
		"abbr": "KW"
	},
	{
		"abbr": "KG",
		"havePhoto": true,
		"name": "Vladimir Ivanov",
		"handle": "astat",
		"width": 640,
		"height": 347
	},
	{
		"havePhoto": true,
		"name": "Ioana Farcas",
		"handle": "ioanafarr",
		"width": 640,
		"height": 960,
		"abbr": "LA"
	},
	{
		"havePhoto": true,
		"name": "Ivars Utināns",
		"handle": "ivoprod",
		"width": 640,
		"height": 480,
		"abbr": "LV"
	},
	{
		"havePhoto": true,
		"name": "Kassem Mahfouz",
		"handle": "studiomahfouz",
		"width": 640,
		"height": 427,
		"abbr": "LB"
	},
	{
		"havePhoto": true,
		"name": "Tatenda Mapigoti",
		"handle": "tmapigoti",
		"width": 640,
		"height": 427,
		"abbr": "LS"
	},
	{
		"havePhoto": true,
		"name": "Jacob Kpehe",
		"handle": "palay",
		"width": 640,
		"height": 480,
		"abbr": "LR"
	},
	{
		"havePhoto": true,
		"name": "Moayad Zaghdani",
		"handle": "moayadzaghdani",
		"width": 640,
		"height": 427,
		"abbr": "LY"
	},
	{
		"havePhoto": true,
		"name": "Henrique Ferreira",
		"handle": "rickpsd",
		"width": 640,
		"height": 427,
		"abbr": "LI"
	},
	{
		"havePhoto": true,
		"name": "Julia Karnavusha",
		"handle": "julkarrr",
		"width": 640,
		"height": 427,
		"abbr": "LT"
	},
	{
		"abbr": "LU",
		"handle": "cedricletsch",
		"havePhoto": true,
		"height": 427,
		"name": "Cedric Letsch",
		"width": 640
	},
	{
		"havePhoto": true,
		"name": "Graphic Node",
		"handle": "graphicnode",
		"width": 640,
		"height": 427,
		"abbr": "MG"
	},
	{
		"havePhoto": true,
		"name": "Ray Aucott",
		"handle": "rayjo",
		"width": 640,
		"height": 853,
		"abbr": "MW"
	},
	{
		"havePhoto": true,
		"name": "Esmonde Yong",
		"handle": "esmonde",
		"width": 640,
		"height": 430,
		"abbr": "MY"
	},
	{
		"havePhoto": true,
		"name": "Hussain Hameed",
		"handle": "surf_maldives",
		"width": 640,
		"height": 480,
		"abbr": "MV"
	},
	{
		"havePhoto": true,
		"name": "Kagou Dicko",
		"handle": "kagou_dicko",
		"width": 640,
		"height": 480,
		"abbr": "ML"
	},
	{
		"abbr": "MT",
		"handle": "mtsap",
		"havePhoto": true,
		"height": 427,
		"name": "Michail Tsapas",
		"width": 640
	},
	{
		"abbr": "MH",
		"handle": null,
		"havePhoto": false,
		"name": null
	},
	{
		"abbr": "MR",
		"handle": null,
		"havePhoto": false,
		"name": null
	},
	{
		"abbr": "MU",
		"handle": null,
		"havePhoto": false,
		"name": null
	},
	{
		"abbr": "MX",
		"handle": "jezar",
		"havePhoto": true,
		"height": 500,
		"name": "Jezael Melgoza",
		"width": 750
	},
	{
		"abbr": "FM",
		"handle": null,
		"havePhoto": false,
		"name": null
	},
	{
		"abbr": "MD",
		"handle": null,
		"havePhoto": false,
		"name": null
	},
	{
		"abbr": "MC",
		"handle": null,
		"havePhoto": false,
		"name": null
	},
	{
		"abbr": "MN",
		"handle": null,
		"havePhoto": false,
		"name": null
	},
	{
		"abbr": "ME",
		"handle": null,
		"havePhoto": false,
		"name": null
	},
	{
		"abbr": "MA",
		"handle": null,
		"havePhoto": false,
		"name": null
	},
	{
		"abbr": "MZ",
		"handle": null,
		"havePhoto": false,
		"name": null
	},
	{
		"abbr": "MM",
		"handle": null,
		"havePhoto": false,
		"name": null
	},
	{
		"abbr": "NA",
		"handle": null,
		"havePhoto": false,
		"name": null
	},
	{
		"abbr": "NP",
		"handle": null,
		"havePhoto": false,
		"name": null
	},
	{
		"abbr": "NL",
		"handle": "muzykalnepodroze",
		"havePhoto": true,
		"height": 1008,
		"name": "Muzykalne Podróże",
		"width": 750
	},
	{
		"abbr": "NC",
		"handle": null,
		"havePhoto": false,
		"name": null
	},
	{
		"abbr": "NZ",
		"handle": null,
		"havePhoto": false,
		"name": null
	},
	{
		"abbr": "NI",
		"handle": null,
		"havePhoto": false,
		"name": null
	},
	{
		"abbr": "NE",
		"handle": null,
		"havePhoto": false,
		"name": null
	},
	{
		"abbr": "NG",
		"handle": null,
		"havePhoto": false,
		"name": null
	},
	{
		"abbr": "KP",
		"handle": null,
		"havePhoto": false,
		"name": null
	},
	{
		"abbr": "MK",
		"handle": "adventurealbania",
		"havePhoto": true,
		"height": 480,
		"name": "Adventure Albania",
		"width": 640
	},
	{
		"abbr": "NO",
		"handle": "jelle_van_leest",
		"havePhoto": true,
		"height": 1333,
		"name": "Jelle Van Leest",
		"width": 750
	},
	{
		"abbr": "OM",
		"handle": null,
		"havePhoto": false,
		"name": null
	},
	{
		"abbr": "PK",
		"handle": null,
		"havePhoto": false,
		"name": null
	},
	{
		"abbr": "PW",
		"handle": null,
		"havePhoto": false,
		"name": null
	},
	{
		"abbr": "PS",
		"handle": null,
		"havePhoto": false,
		"name": null
	},
	{
		"abbr": "PA",
		"handle": null,
		"havePhoto": false,
		"name": null
	},
	{
		"abbr": "PG",
		"handle": null,
		"havePhoto": false,
		"name": null
	},
	{
		"abbr": "PY",
		"handle": null,
		"havePhoto": false,
		"name": null
	},
	{
		"abbr": "PE",
		"handle": null,
		"havePhoto": false,
		"name": null
	},
	{
		"abbr": "PH",
		"handle": null,
		"havePhoto": false,
		"name": null
	},
	{
		"abbr": "PL",
		"handle": null,
		"havePhoto": false,
		"name": null
	},
	{
		"abbr": "PT",
		"handle": "alexrvasey",
		"havePhoto": true,
		"height": 1000,
		"name": "Alex Vasey",
		"width": 750
	},
	{
		"abbr": "PR",
		"handle": "zetong",
		"havePhoto": true,
		"height": 640,
		"name": "Zetong Li",
		"width": 640
	},
	{
		"abbr": "QA",
		"handle": "erprekurat",
		"havePhoto": true,
		"height": 427,
		"name": "Radoslaw Prekurat",
		"width": 640
	},
	{
		"abbr": "RO",
		"handle": "majklvelner",
		"havePhoto": true,
		"height": 427,
		"name": "Majkl Velner",
		"width": 640
	},
	{
		"abbr": "RU",
		"handle": "nikolayv",
		"havePhoto": true,
		"height": 827,
		"name": "Nikolay Vorobyev",
		"width": 640
	},
	{
		"abbr": "RW",
		"handle": "niyomax",
		"havePhoto": false,
		"name": "maxime niyomwungeri"
	},
	{
		"abbr": "KN",
		"handle": "wizzi95",
		"havePhoto": true,
		"height": 480,
		"name": "Omar Martin",
		"width": 640
	},
	{
		"abbr": "LC",
		"handle": "jannerboy62",
		"havePhoto": true,
		"height": 427,
		"name": "Nick Fewings",
		"width": 640
	},
	{
		"abbr": "VC",
		"handle": "iplaytheairguitar",
		"havePhoto": true,
		"height": 480,
		"name": "George Apodaca",
		"width": 640
	},
	{
		"abbr": "WS",
		"handle": "amromzes",
		"havePhoto": true,
		"height": 960,
		"name": "Romeo Leaupepe Su’a",
		"width": 640
	},
	{
		"abbr": "SM",
		"handle": "philipmyr",
		"havePhoto": true,
		"height": 360,
		"name": "Philip Myrtorp",
		"width": 640
	},
	{
		"abbr": "ST",
		"handle": null,
		"havePhoto": false,
		"name": null
	},
	{
		"abbr": "SA",
		"handle": "hydngallery",
		"havePhoto": true,
		"height": 853,
		"name": "Haidan",
		"width": 640
	},
	{
		"abbr": "SN",
		"handle": "tongni",
		"havePhoto": true,
		"height": 427,
		"name": "TD AD",
		"width": 640
	},
	{
		"abbr": "RS",
		"handle": "cirkanye",
		"havePhoto": true,
		"height": 427,
		"name": "Nikola Cirkovic",
		"width": 640
	},
	{
		"abbr": "SC",
		"handle": "cacciahands",
		"havePhoto": true,
		"height": 480,
		"name": "Christian Cacciamani",
		"width": 640
	},
	{
		"abbr": "SL",
		"handle": "abdulaisayni80",
		"havePhoto": true,
		"height": 360,
		"name": "Abdulai Sayni",
		"width": 640
	},
	{
		"abbr": "SG",
		"handle": "unfilteredkopi",
		"havePhoto": true,
		"height": 480,
		"name": "Swapnil Bapat",
		"width": 640
	},
	{
		"abbr": "SI",
		"handle": "nevenkrcmarek",
		"havePhoto": true,
		"height": 404,
		"name": "Neven Krcmarek",
		"width": 640
	},
	{
		"abbr": "SB",
		"handle": "glt23",
		"havePhoto": true,
		"height": 359,
		"name": "Gilly Tanabose",
		"width": 640
	},
	{
		"abbr": "SO",
		"handle": "saacid",
		"havePhoto": true,
		"height": 480,
		"name": "Saacid Ahmed",
		"width": 640
	},
	{
		"abbr": "ZA",
		"handle": "linaloos",
		"havePhoto": true,
		"height": 427,
		"name": "Lina Loos",
		"width": 640
	},
	{
		"abbr": "KR",
		"handle": "robsonhmorgan",
		"havePhoto": true,
		"height": 960,
		"name": "Robson Hatsukami Morgan",
		"width": 640
	},
	{
		"abbr": "SS",
		"handle": "a7med7",
		"havePhoto": true,
		"height": 853,
		"name": "Ahmed Alghali",
		"width": 640
	},
	{
		"abbr": "ES",
		"handle": "whatyouhide",
		"havePhoto": true,
		"height": 1125,
		"name": "Andrea Leopardi",
		"width": 750
	},
	{
		"abbr": "LK",
		"handle": "smeshny",
		"havePhoto": true,
		"height": 360,
		"name": "Siarhei Palishchuk",
		"width": 640
	},
	{
		"abbr": "SD",
		"handle": "mohammedmojahed",
		"havePhoto": true,
		"height": 480,
		"name": "Mohammed Mojahed",
		"width": 640
	},
	{
		"abbr": "SR",
		"handle": "vincentvanzalinge",
		"havePhoto": true,
		"height": 427,
		"name": "Vincent van Zalinge",
		"width": 640
	},
	{
		"abbr": "SE",
		"handle": "scottstuckle3",
		"havePhoto": true,
		"height": 427,
		"name": "Scott Stuckle",
		"width": 640
	},
	{
		"abbr": "CH",
		"handle": "rickpsd",
		"havePhoto": true,
		"height": 426,
		"name": "Henrique Ferreira",
		"width": 640
	},
	{
		"abbr": "SY",
		"handle": "photo98shoot",
		"havePhoto": true,
		"height": 427,
		"name": "abd sarakbi",
		"width": 640
	},
	{
		"abbr": "TR",
		"handle": "shahjafar",
		"havePhoto": true,
		"height": 672,
		"name": "Shah Abdullah",
		"width": 640
	},
	{
		"abbr": "TW",
		"handle": null,
		"havePhoto": false,
		"name": null
	},
	{
		"abbr": "TJ",
		"handle": "etienneflorent",
		"havePhoto": true,
		"height": 360,
		"name": "Etienne Dayer",
		"width": 640
	},
	{
		"abbr": "TZ",
		"handle": "huchenme",
		"havePhoto": true,
		"height": 960,
		"name": "Hu Chen",
		"width": 640
	},
	{
		"abbr": "TZ",
		"handle": "mr_chief",
		"havePhoto": true,
		"height": 960,
		"name": "Matthew Spiteri",
		"width": 640
	},
	{
		"abbr": "TH",
		"handle": "robinnoguier",
		"havePhoto": true,
		"height": 427,
		"name": "Robin Noguier",
		"width": 640
	},
	{
		"abbr": "TL",
		"handle": "tanushreerao",
		"havePhoto": true,
		"height": 479,
		"name": "Tanushree Rao",
		"width": 640
	},
	{
		"abbr": "TG",
		"handle": "ingeborgkorme",
		"havePhoto": true,
		"height": 960,
		"name": "Ingeborg Korme",
		"width": 640
	},
	{
		"abbr": "TO",
		"handle": "russmail",
		"havePhoto": true,
		"height": 427,
		"name": "Vince Russell",
		"width": 640
	},
	{
		"abbr": "TT",
		"handle": "thrustonbenny",
		"havePhoto": true,
		"height": 360,
		"name": "Thruston Benny",
		"width": 640
	},
	{
		"abbr": "TN",
		"handle": "haythemgataa",
		"havePhoto": true,
		"height": 353,
		"name": "Haythem Gataa",
		"width": 640
	},
	{
		"abbr": "TM",
		"handle": "igrigoriy",
		"havePhoto": true,
		"height": 363,
		"name": "Григорий Захарьян",
		"width": 640
	},
	{
		"abbr": "TV",
		"handle": "winstonchen",
		"havePhoto": false,
		"name": "Winston Chen"
	},
	{
		"abbr": "UG",
		"handle": "randominstitute",
		"havePhoto": true,
		"height": 427,
		"name": "Random Institute",
		"width": 640
	},
	{
		"abbr": "UA",
		"handle": "albovsky",
		"havePhoto": true,
		"height": 400,
		"name": "Glib Albovsky",
		"width": 640
	},
	{
		"abbr": "AE",
		"handle": "div8018",
		"havePhoto": true,
		"height": 427,
		"name": "Divjot Ratra",
		"width": 640
	},
	{
		"abbr": "GB",
		"handle": "bendavisual",
		"havePhoto": true,
		"height": 427,
		"name": "Benjamin Davies",
		"width": 640
	},
	{
		"abbr": "US",
		"handle": "impatrickt",
		"havePhoto": true,
		"height": 426,
		"name": "Patrick Tomasso",
		"width": 640
	},
	{
		"abbr": "UZ",
		"handle": "far5n10v",
		"havePhoto": true,
		"height": 512,
		"name": "Farhodjon Chinberdiev",
		"width": 640
	},
	{
		"abbr": "VE",
		"handle": "arq_blee",
		"havePhoto": true,
		"height": 303,
		"name": "Bona Lee",
		"width": 640
	},
	{
		"abbr": "EH",
		"handle": "leret",
		"havePhoto": true,
		"height": 480,
		"name": "Carlos Leret",
		"width": 640
	},
	{
		"abbr": "YE",
		"handle": "",
		"havePhoto": true,
		"height": 446,
		"name": "Almwald Alezzey",
		"width": 640
	},
	{
		"abbr": "ZM",
		"handle": "pauljmilley",
		"havePhoto": true,
		"height": 960,
		"name": "paul milley",
		"width": 640
	},
	{
		"abbr": "UY",
		"handle": "pedroslinger",
		"havePhoto": true,
		"height": 1125,
		"name": "Pedro Slinger",
		"width": 750
	},
	{
		"abbr": "VU",
		"handle": null,
		"havePhoto": false,
		"name": null
	},
	{
		"abbr": "VN",
		"handle": "ammiengo",
		"havePhoto": true,
		"height": 500,
		"name": "Ammie Ngo",
		"width": 750
	},
	{
		"abbr": "ZW",
		"handle": null,
		"havePhoto": false,
		"name": null
	}
]
